nudenet/320n.onnx
nudenet/__init__.py
nudenet/nudenet.py
nudenet-3.4.1.dist-info/LICENSE
nudenet-3.4.1.dist-info/LICENSE.md
nudenet-3.4.1.dist-info/METADATA
nudenet-3.4.1.dist-info/WHEEL
nudenet-3.4.1.dist-info/entry_points.txt
nudenet-3.4.1.dist-info/top_level.txt
nudenet-3.4.1.dist-info/RECORD
