Metadata-Version: 2.1
Name: nudenet
Version: 3.4.1
Summary: Lightweight Nudity Detection
Home-page: https://github.com/notAI-tech/nudenet
Author: BEDAPUDI PRANEETH
Author-email: praneeth@bpraneeth.com
License: MIT
Classifier: License :: OSI Approved :: MIT License
Classifier: Programming Language :: Python
Classifier: Programming Language :: Python :: 3
Classifier: Programming Language :: Python :: 3.6
Classifier: Programming Language :: Python :: Implementation :: CPython
Requires-Python: >=3.6.0
License-File: LICENSE
License-File: LICENSE.md
Requires-Dist: numpy
Requires-Dist: onnxruntime
Requires-Dist: opencv-python-headless
